Torricelli/__init__.py
Torricelli/__main__.py
Torricelli/torricelli.py
Torricelli/imports/GUI_InsertManualValues.py
Torricelli/imports/GUI_MainWindow.py
Torricelli/imports/GUI_Regroup.py
Torricelli/imports/GUI_RemoveAll.py
Torricelli/imports/GUI_Rename.py
Torricelli/imports/GUI_SymbolList.py
Torricelli/imports/Geometry.png
Torricelli/imports/Torricelli_icon.png
Torricelli/imports/chi_2_Pearson.png
Torricelli/imports/chi_red2.png
Torricelli/imports/pyArgand.py
Torricelli/imports/Databases/Database references.txt
Torricelli/imports/Databases/Nondipolar_parameters_of_angular_distribution_Z1to100.ini
Torricelli/imports/Databases/f0.csv
Torricelli/imports/Databases/DW/DW_Gao_Elemental_highT.csv
Torricelli/imports/Databases/DW/DW_Gao_Elemental_lowT.csv
Torricelli/imports/Databases/DW/DW_Sears.csv
Torricelli/imports/Databases/DW/DW_Zywietz_C.csv
Torricelli/imports/Databases/DW/DW_Zywietz_Si.csv
Torricelli/imports/Databases/Lattices/AtomCoordinates_HCP.csv
Torricelli/imports/Databases/Lattices/AtomCoordinates_HEX Tetradymite.csv
Torricelli/imports/Databases/Lattices/AtomCoordinates_HEX Wurtzite.csv
Torricelli/imports/Databases/Lattices/AtomCoordinates_baseCentered.csv
Torricelli/imports/Databases/Lattices/AtomCoordinates_bodyCentered.csv
Torricelli/imports/Databases/Lattices/AtomCoordinates_diamond.csv
Torricelli/imports/Databases/Lattices/AtomCoordinates_diamond_otherOrigin.csv
Torricelli/imports/Databases/Lattices/AtomCoordinates_faceCentered.csv
Torricelli/imports/Databases/Lattices/AtomCoordinates_primitive.csv
Torricelli/imports/Databases/Lattices/CrystallographicData_Compound.csv
Torricelli/imports/Databases/Lattices/CrystallographicData_Elemental.csv
Torricelli/imports/Databases/f1 and f2/ac.nff
Torricelli/imports/Databases/f1 and f2/ag.nff
Torricelli/imports/Databases/f1 and f2/al.nff
Torricelli/imports/Databases/f1 and f2/ar.nff
Torricelli/imports/Databases/f1 and f2/as.nff
Torricelli/imports/Databases/f1 and f2/at.nff
Torricelli/imports/Databases/f1 and f2/au.nff
torricelli-4.0.1.dist-info/LICENSE
torricelli-4.0.1.dist-info/METADATA
torricelli-4.0.1.dist-info/WHEEL
torricelli-4.0.1.dist-info/top_level.txt
torricelli-4.0.1.dist-info/RECORD
