Metadata-Version: 2.1
Name: torricelli
Version: 4.0.1
Summary: UNKNOWN
Home-page: https://github.com/fposseik/Torricelli
Author: Francois C. Bocquet
Author-email: f.posseik@fz-juelich.de
License: UNKNOWN
Platform: UNKNOWN
Classifier: Programming Language :: Python :: 3
Classifier: License :: OSI Approved :: GNU General Public License v3 (GPLv3)
Classifier: Operating System :: OS Independent
Requires-Python: ~=3.7
Requires-Dist: lmfit
Requires-Dist: pyqtgraph
Requires-Dist: h5py
Requires-Dist: numpy
Requires-Dist: scipy
